libertem_live/__init__.py
libertem_live/__version__.py
libertem_live/_baked_revision.py
libertem_live/api.py
libertem_live/hooks.py
libertem_live/versioning.py
libertem_live/detectors/LICENSE
libertem_live/detectors/__init__.py
libertem_live/detectors/common.py
libertem_live/detectors/asi_tpx3/__init__.py
libertem_live/detectors/asi_tpx3/acquisition.py
libertem_live/detectors/asi_tpx3/connection.py
libertem_live/detectors/asi_tpx3/controller.py
libertem_live/detectors/asi_tpx3/sim.py
libertem_live/detectors/base/__init__.py
libertem_live/detectors/base/acquisition.py
libertem_live/detectors/base/connection.py
libertem_live/detectors/base/controller.py
libertem_live/detectors/dectris/DEigerClient.py
libertem_live/detectors/dectris/__init__.py
libertem_live/detectors/dectris/acquisition.py
libertem_live/detectors/dectris/common.py
libertem_live/detectors/dectris/connection.py
libertem_live/detectors/dectris/controller.py
libertem_live/detectors/dectris/sim.py
libertem_live/detectors/memory/__init__.py
libertem_live/detectors/memory/acquisition.py
libertem_live/detectors/merlin/__init__.py
libertem_live/detectors/merlin/acquisition.py
libertem_live/detectors/merlin/connection.py
libertem_live/detectors/merlin/control.py
libertem_live/detectors/merlin/controller.py
libertem_live/detectors/merlin/data.py
libertem_live/detectors/merlin/decoders.py
libertem_live/detectors/merlin/sim.py
libertem_live/detectors/merlin/tango_server.py
libertem_live/detectors/merlin/utils.py
libertem_live/udf/__init__.py
libertem_live/udf/monitor.py
libertem_live/udf/record.py
libertem_live-0.2.1.dist-info/LICENSE
libertem_live-0.2.1.dist-info/METADATA
libertem_live-0.2.1.dist-info/WHEEL
libertem_live-0.2.1.dist-info/entry_points.txt
libertem_live-0.2.1.dist-info/top_level.txt
libertem_live-0.2.1.dist-info/RECORD
