Metadata-Version: 2.1
Name: libertem-live
Version: 0.2.1
Summary: Live processing with LiberTEM
Home-page: https://libertem.github.io/LiberTEM-live
Author: the LiberTEM team
Author-email: libertem-dev@googlegroups.com
License: GPL v3
Keywords: electron microscopy
Classifier: Development Status :: 4 - Beta
Classifier: Programming Language :: Python :: 3.7
Classifier: Programming Language :: Python :: 3.8
Classifier: Programming Language :: Python :: 3.9
Classifier: Programming Language :: Python :: 3.10
Classifier: License :: OSI Approved :: GNU General Public License v3 (GPLv3)
Classifier: Operating System :: POSIX :: Linux
Classifier: Operating System :: MacOS :: MacOS X
Classifier: Operating System :: Microsoft :: Windows
Classifier: Environment :: Console
Classifier: Intended Audience :: Science/Research
Classifier: Intended Audience :: End Users/Desktop
Classifier: Intended Audience :: Developers
Classifier: Natural Language :: English
Classifier: Topic :: Scientific/Engineering
Classifier: Topic :: Scientific/Engineering :: Physics
Classifier: Topic :: Scientific/Engineering :: Visualization
Requires-Python: >=3.7
License-File: LICENSE
Requires-Dist: libertem (>=0.11.0.dev0)
Requires-Dist: numpy
Requires-Dist: click
Requires-Dist: tqdm
Requires-Dist: numba
Requires-Dist: opentelemetry-api
Requires-Dist: sparseconverter
Requires-Dist: libertem-dectris (>=0.2.10)
Requires-Dist: libertem-asi-tpx3 (>=0.2.10)
Provides-Extra: pymemfd
Requires-Dist: pymemfd ; extra == 'pymemfd'
Provides-Extra: pytango
Requires-Dist: pytango ; extra == 'pytango'
Provides-Extra: sim
Requires-Dist: flask ; extra == 'sim'
